[
    {
        "country": "BB",
        "name": "Welchman Hall",
        "lat": "13.18676",
        "lng": "-59.57663"
    },
    {
        "country": "BB",
        "name": "Crane",
        "lat": "13.10487",
        "lng": "-59.44861"
    },
    {
        "country": "BB",
        "name": "Speightstown",
        "lat": "13.25072",
        "lng": "-59.64396"
    },
    {
        "country": "BB",
        "name": "Oistins",
        "lat": "13.07067",
        "lng": "-59.54637"
    },
    {
        "country": "BB",
        "name": "Holetown",
        "lat": "13.18672",
        "lng": "-59.63808"
    },
    {
        "country": "BB",
        "name": "Greenland",
        "lat": "13.25808",
        "lng": "-59.57763"
    },
    {
        "country": "BB",
        "name": "Four Cross Roads",
        "lat": "13.17018",
        "lng": "-59.52186"
    },
    {
        "country": "BB",
        "name": "Checker Hall",
        "lat": "13.28445",
        "lng": "-59.64223"
    },
    {
        "country": "BB",
        "name": "Bridgetown",
        "lat": "13.10732",
        "lng": "-59.62021"
    },
    {
        "country": "BB",
        "name": "Bathsheba",
        "lat": "13.21133",
        "lng": "-59.52596"
    }
]